AUTHORS
COPYING
MANIFEST.in
README
development.ini
setup.py
moksha/__init__.py
moksha.hub.egg-info/PKG-INFO
moksha.hub.egg-info/SOURCES.txt
moksha.hub.egg-info/dependency_links.txt
moksha.hub.egg-info/entry_points.txt
moksha.hub.egg-info/namespace_packages.txt
moksha.hub.egg-info/pbr.json
moksha.hub.egg-info/requires.txt
moksha.hub.egg-info/top_level.txt
moksha/hub/__init__.py
moksha/hub/hub.py
moksha/hub/messaging.py
moksha/hub/monitoring.py
moksha/hub/reactor.py
moksha/hub/amqp/__init__.py
moksha/hub/amqp/base.py
moksha/hub/amqp/pyamqplib.py
moksha/hub/amqp/qpid010.py
moksha/hub/amqp/qpid08.py
moksha/hub/api/__init__.py
moksha/hub/api/consumer.py
moksha/hub/api/producer.py
moksha/hub/stomp/__init__.py
moksha/hub/stomp/protocol.py
moksha/hub/stomp/stomp.py
moksha/hub/tests/__init__.py
moksha/hub/tests/test_hub.py
moksha/hub/tests/test_websockets.py
moksha/hub/zeromq/__init__.py
moksha/hub/zeromq/base.py
moksha/hub/zeromq/zeromq.py