Metadata-Version: 1.0
Name: moksha.hub
Version: 1.4.6
Summary: Hub components for Moksha.
Home-page: http://moksha.fedorahosted.org
Author: Luke Macken, John (J5) Palmieri, Mairin Duffy, and Ralph Bean
Author-email: UNKNOWN
License: UNKNOWN
Platform: UNKNOWN
